LFSR32.sv
module LFSR32(
  input clk,
  output reg [31:0] num
);

  initial num = 32'd15;

  wire fb = num[31];

  always_ff @(posedge clk) begin
    integer i;
    for (i = 31; i > 0; i = i - 1) begin
      num[i] <= num[i-1];
    num[0] <= num[30] ^ fb;
    end
  end
endmodule

LFSR32_tb.sv
`timescale 1ns/1ps

module LFSR32_tb;
    reg clk;
    wire [31:0] num;

    LFSR32 uut (
        .clk(clk),
        .num(num)
    );

    // Gerador de clock
    initial begin
        clk = 0;
        forever #5 clk = ~clk;  // Gera um clock com período de 10 unidades de tempo (5 + 5)
    end

    // Simulação
    initial begin
        $dumpfile("LFSR32_tb.vcd"); // Para gerar um arquivo de saída para visualização no GTKWave
        $dumpvars(0, LFSR32_tb);

        #1000;  // Simula por 1000 unidades de tempo
        $finish;
    end
endmodule

LFSR32_tb.vcd
$date
	Thu Sep 05 18:39:04 2024
$end
$version
	Icarus Verilog
$end
$timescale
	1ps
$end
$scope module LFSR32_tb $end
$var wire 32 ! num [31:0] $end
$var reg 1 " clk $end
$scope module uut $end
$var wire 1 " clk $end
$var wire 1 # fb $end
$var reg 32 $ num [31:0] $end
$scope begin $unm_blk_1 $end
$var integer 32 % i [31:0] $end
$upscope $end
$upscope $end
$upscope $end
$enddefinitions $end
#0
$dumpvars
bx %
b1111 $
0#
0"
b1111 !
$end
#5000
b11110 !
b11110 $
b0 %
1"
#10000
0"
#15000
b111100 !
b111100 $
b0 %
1"
#20000
0"
#25000
b1111000 !
b1111000 $
b0 %
1"
#30000
0"
#35000
b11110000 !
b11110000 $
b0 %
1"
#40000
0"
#45000
b111100000 !
b111100000 $
b0 %
1"
#50000
0"
#55000
b1111000000 !
b1111000000 $
b0 %
1"
#60000
0"
#65000
b11110000000 !
b11110000000 $
b0 %
1"
#70000
0"
#75000
b111100000000 !
b111100000000 $
b0 %
1"
#80000
0"
#85000
b1111000000000 !
b1111000000000 $
b0 %
1"
#90000
0"
#95000
b11110000000000 !
b11110000000000 $
b0 %
1"
#100000
0"
#105000
b111100000000000 !
b111100000000000 $
b0 %
1"
#110000
0"
#115000
b1111000000000000 !
b1111000000000000 $
b0 %
1"
#120000
0"
#125000
b11110000000000000 !
b11110000000000000 $
b0 %
1"
#130000
0"
#135000
b111100000000000000 !
b111100000000000000 $
b0 %
1"
#140000
0"
#145000
b1111000000000000000 !
b1111000000000000000 $
b0 %
1"
#150000
0"
#155000
b11110000000000000000 !
b11110000000000000000 $
b0 %
1"
#160000
0"
#165000
b111100000000000000000 !
b111100000000000000000 $
b0 %
1"
#170000
0"
#175000
b1111000000000000000000 !
b1111000000000000000000 $
b0 %
1"
#180000
0"
#185000
b11110000000000000000000 !
b11110000000000000000000 $
b0 %
1"
#190000
0"
#195000
b111100000000000000000000 !
b111100000000000000000000 $
b0 %
1"
#200000
0"
#205000
b1111000000000000000000000 !
b1111000000000000000000000 $
b0 %
1"
#210000
0"
#215000
b11110000000000000000000000 !
b11110000000000000000000000 $
b0 %
1"
#220000
0"
#225000
b111100000000000000000000000 !
b111100000000000000000000000 $
b0 %
1"
#230000
0"
#235000
b1111000000000000000000000000 !
b1111000000000000000000000000 $
b0 %
1"
#240000
0"
#245000
b11110000000000000000000000000 !
b11110000000000000000000000000 $
b0 %
1"
#250000
0"
#255000
b111100000000000000000000000000 !
b111100000000000000000000000000 $
b0 %
1"
#260000
0"
#265000
b1111000000000000000000000000000 !
b1111000000000000000000000000000 $
b0 %
1"
#270000
0"
#275000
1#
b11110000000000000000000000000001 !
b11110000000000000000000000000001 $
b0 %
1"
#280000
0"
#285000
b11100000000000000000000000000010 !
b11100000000000000000000000000010 $
b0 %
1"
#290000
0"
#295000
b11000000000000000000000000000100 !
b11000000000000000000000000000100 $
b0 %
1"
#300000
0"
#305000
b10000000000000000000000000001000 !
b10000000000000000000000000001000 $
b0 %
1"
#310000
0"
#315000
0#
b10001 !
b10001 $
b0 %
1"
#320000
0"
#325000
b100010 !
b100010 $
b0 %
1"
#330000
0"
#335000
b1000100 !
b1000100 $
b0 %
1"
#340000
0"
#345000
b10001000 !
b10001000 $
b0 %
1"
#350000
0"
#355000
b100010000 !
b100010000 $
b0 %
1"
#360000
0"
#365000
b1000100000 !
b1000100000 $
b0 %
1"
#370000
0"
#375000
b10001000000 !
b10001000000 $
b0 %
1"
#380000
0"
#385000
b100010000000 !
b100010000000 $
b0 %
1"
#390000
0"
#395000
b1000100000000 !
b1000100000000 $
b0 %
1"
#400000
0"
#405000
b10001000000000 !
b10001000000000 $
b0 %
1"
#410000
0"
#415000
b100010000000000 !
b100010000000000 $
b0 %
1"
#420000
0"
#425000
b1000100000000000 !
b1000100000000000 $
b0 %
1"
#430000
0"
#435000
b10001000000000000 !
b10001000000000000 $
b0 %
1"
#440000
0"
#445000
b100010000000000000 !
b100010000000000000 $
b0 %
1"
#450000
0"
#455000
b1000100000000000000 !
b1000100000000000000 $
b0 %
1"
#460000
0"
#465000
b10001000000000000000 !
b10001000000000000000 $
b0 %
1"
#470000
0"
#475000
b100010000000000000000 !
b100010000000000000000 $
b0 %
1"
#480000
0"
#485000
b1000100000000000000000 !
b1000100000000000000000 $
b0 %
1"
#490000
0"
#495000
b10001000000000000000000 !
b10001000000000000000000 $
b0 %
1"
#500000
0"
#505000
b100010000000000000000000 !
b100010000000000000000000 $
b0 %
1"
#510000
0"
#515000
b1000100000000000000000000 !
b1000100000000000000000000 $
b0 %
1"
#520000
0"
#525000
b10001000000000000000000000 !
b10001000000000000000000000 $
b0 %
1"
#530000
0"
#535000
b100010000000000000000000000 !
b100010000000000000000000000 $
b0 %
1"
#540000
0"
#545000
b1000100000000000000000000000 !
b1000100000000000000000000000 $
b0 %
1"
#550000
0"
#555000
b10001000000000000000000000000 !
b10001000000000000000000000000 $
b0 %
1"
#560000
0"
#565000
b100010000000000000000000000000 !
b100010000000000000000000000000 $
b0 %
1"
#570000
0"
#575000
b1000100000000000000000000000000 !
b1000100000000000000000000000000 $
b0 %
1"
#580000
0"
#585000
1#
b10001000000000000000000000000001 !
b10001000000000000000000000000001 $
b0 %
1"
#590000
0"
#595000
0#
b10000000000000000000000000011 !
b10000000000000000000000000011 $
b0 %
1"
#600000
0"
#605000
b100000000000000000000000000110 !
b100000000000000000000000000110 $
b0 %
1"
#610000
0"
#615000
b1000000000000000000000000001100 !
b1000000000000000000000000001100 $
b0 %
1"
#620000
0"
#625000
1#
b10000000000000000000000000011001 !
b10000000000000000000000000011001 $
b0 %
1"
#630000
0"
#635000
0#
b110011 !
b110011 $
b0 %
1"
#640000
0"
#645000
b1100110 !
b1100110 $
b0 %
1"
#650000
0"
#655000
b11001100 !
b11001100 $
b0 %
1"
#660000
0"
#665000
b110011000 !
b110011000 $
b0 %
1"
#670000
0"
#675000
b1100110000 !
b1100110000 $
b0 %
1"
#680000
0"
#685000
b11001100000 !
b11001100000 $
b0 %
1"
#690000
0"
#695000
b110011000000 !
b110011000000 $
b0 %
1"
#700000
0"
#705000
b1100110000000 !
b1100110000000 $
b0 %
1"
#710000
0"
#715000
b11001100000000 !
b11001100000000 $
b0 %
1"
#720000
0"
#725000
b110011000000000 !
b110011000000000 $
b0 %
1"
#730000
0"
#735000
b1100110000000000 !
b1100110000000000 $
b0 %
1"
#740000
0"
#745000
b11001100000000000 !
b11001100000000000 $
b0 %
1"
#750000
0"
#755000
b110011000000000000 !
b110011000000000000 $
b0 %
1"
#760000
0"
#765000
b1100110000000000000 !
b1100110000000000000 $
b0 %
1"
#770000
0"
#775000
b11001100000000000000 !
b11001100000000000000 $
b0 %
1"
#780000
0"
#785000
b110011000000000000000 !
b110011000000000000000 $
b0 %
1"
#790000
0"
#795000
b1100110000000000000000 !
b1100110000000000000000 $
b0 %
1"
#800000
0"
#805000
b11001100000000000000000 !
b11001100000000000000000 $
b0 %
1"
#810000
0"
#815000
b110011000000000000000000 !
b110011000000000000000000 $
b0 %
1"
#820000
0"
#825000
b1100110000000000000000000 !
b1100110000000000000000000 $
b0 %
1"
#830000
0"
#835000
b11001100000000000000000000 !
b11001100000000000000000000 $
b0 %
1"
#840000
0"
#845000
b110011000000000000000000000 !
b110011000000000000000000000 $
b0 %
1"
#850000
0"
#855000
b1100110000000000000000000000 !
b1100110000000000000000000000 $
b0 %
1"
#860000
0"
#865000
b11001100000000000000000000000 !
b11001100000000000000000000000 $
b0 %
1"
#870000
0"
#875000
b110011000000000000000000000000 !
b110011000000000000000000000000 $
b0 %
1"
#880000
0"
#885000
b1100110000000000000000000000000 !
b1100110000000000000000000000000 $
b0 %
1"
#890000
0"
#895000
1#
b11001100000000000000000000000001 !
b11001100000000000000000000000001 $
b0 %
1"
#900000
0"
#905000
b10011000000000000000000000000010 !
b10011000000000000000000000000010 $
b0 %
1"
#910000
0"
#915000
0#
b110000000000000000000000000101 !
b110000000000000000000000000101 $
b0 %
1"
#920000
0"
#925000
b1100000000000000000000000001010 !
b1100000000000000000000000001010 $
b0 %
1"
#930000
0"
#935000
1#
b11000000000000000000000000010101 !
b11000000000000000000000000010101 $
b0 %
1"
#940000
0"
#945000
b10000000000000000000000000101010 !
b10000000000000000000000000101010 $
b0 %
1"
#950000
0"
#955000
0#
b1010101 !
b1010101 $
b0 %
1"
#960000
0"
#965000
b10101010 !
b10101010 $
b0 %
1"
#970000
0"
#975000
b101010100 !
b101010100 $
b0 %
1"
#980000
0"
#985000
b1010101000 !
b1010101000 $
b0 %
1"
#990000
0"
#995000
b10101010000 !
b10101010000 $
b0 %
1"
